synthesized3/__init__.py
synthesized3/api.cp310-win_amd64.pyd
synthesized3/api.py
synthesized3/cmd_line.cp310-win_amd64.pyd
synthesized3/cmd_line.py
synthesized3/column_type.cp310-win_amd64.pyd
synthesized3/column_type.py
synthesized3/nature.cp310-win_amd64.pyd
synthesized3/nature.py
synthesized3/schema.cp310-win_amd64.pyd
synthesized3/schema.py
synthesized3/schema_test.py
synthesized3/version.cp310-win_amd64.pyd
synthesized3/version.py
synthesized3/_licence/__init__.py
synthesized3/_licence/analytics.cp310-win_amd64.pyd
synthesized3/_licence/analytics.py
synthesized3/_licence/exceptions.cp310-win_amd64.pyd
synthesized3/_licence/exceptions.py
synthesized3/_licence/features.cp310-win_amd64.pyd
synthesized3/_licence/features.py
synthesized3/_licence/licence.cp310-win_amd64.pyd
synthesized3/_licence/licence.py
synthesized3/_licence/prompt.cp310-win_amd64.pyd
synthesized3/_licence/prompt.py
synthesized3/data_interface/__init__.py
synthesized3/data_interface/data_interface.cp310-win_amd64.pyd
synthesized3/data_interface/data_interface.py
synthesized3/data_interface/data_interface_factory.cp310-win_amd64.pyd
synthesized3/data_interface/data_interface_factory.py
synthesized3/data_interface/data_interface_factory_test.py
synthesized3/data_interface/data_interface_test.py
synthesized3/data_interface/data_interfaces/__init__.py
synthesized3/data_interface/data_interfaces/pandas_data_interface.cp310-win_amd64.pyd
synthesized3/data_interface/data_interfaces/pandas_data_interface.py
synthesized3/data_interface/data_interfaces/pandas_data_interface_data_test.py
synthesized3/data_interface/data_interfaces/pandas_data_interface_general_test.py
synthesized3/data_interface/data_interfaces/pandas_utils.cp310-win_amd64.pyd
synthesized3/data_interface/data_interfaces/pandas_utils.py
synthesized3/data_interface/data_interfaces/pandas_utils_test.py
synthesized3/data_interface/data_interfaces/spark_data_interface.cp310-win_amd64.pyd
synthesized3-3.2.dist-info/LICENSE.md
synthesized3-3.2.dist-info/METADATA
synthesized3-3.2.dist-info/WHEEL
synthesized3-3.2.dist-info/entry_points.txt
synthesized3-3.2.dist-info/top_level.txt
synthesized3-3.2.dist-info/RECORD
