Metadata-Version: 2.1
Name: synthesized3
Version: 3.2
Summary: Synthesized SDK.
Author-email: "Synthesized Ltd." <sdk-team@synthesized.io>
License: Copyright 2018 Synthesized LTD
Project-URL: homepage, https://synthesized.io
Project-URL: repository, https://github.com/synthesized-io/sdk
Keywords: synthetic,generative,data
Platform: MacOS
Platform: Linux
Platform: Windows
Classifier: Development Status :: 4 - Beta
Classifier: License :: Other/Proprietary License
Classifier: Intended Audience :: Developers
Classifier: Intended Audience :: Financial and Insurance Industry
Classifier: Intended Audience :: Information Technology
Classifier: Intended Audience :: Healthcare Industry
Classifier: Operating System :: MacOS
Classifier: Operating System :: POSIX
Classifier: Operating System :: Unix
Classifier: Programming Language :: Python :: 3
Classifier: Programming Language :: Python :: 3 :: Only
Classifier: Programming Language :: Python :: 3.9
Classifier: Programming Language :: Python :: 3.10
Classifier: Programming Language :: Python :: 3.11
Classifier: Topic :: Scientific/Engineering
Classifier: Topic :: Scientific/Engineering :: Artificial Intelligence
Requires-Python: >=3.9
License-File: LICENSE.md
Requires-Dist: ff3
Requires-Dist: numpy
Requires-Dist: pandas
Requires-Dist: prompt-toolkit >=3.0.0
Requires-Dist: pyarrow
Requires-Dist: pycryptodome
Requires-Dist: pyspark >=3.4
Requires-Dist: pydantic <2
Requires-Dist: rsa >=4.7
Requires-Dist: rstr
Requires-Dist: scipy
Requires-Dist: tensorflow-probability <0.24,>=0.20
Requires-Dist: pyyaml
Requires-Dist: tensorflow-cpu <2.16,>=2.13.0 ; platform_machine != "arm64" or platform_system != "Darwin"
Requires-Dist: tensorflow-macos <2.16,>=2.13.0 ; platform_machine == "arm64" and platform_system == "Darwin"
Provides-Extra: dev
Requires-Dist: build ; extra == 'dev'
Requires-Dist: cython >=3.0.2 ; extra == 'dev'
Requires-Dist: jupyterlab ; extra == 'dev'
Requires-Dist: pylint ; extra == 'dev'
Requires-Dist: pre-commit ; extra == 'dev'
Requires-Dist: pylint-pydantic ; extra == 'dev'
Provides-Extra: evaluation
Requires-Dist: cython >=3.0.2 ; extra == 'evaluation'
Requires-Dist: fire ==0.5.0 ; extra == 'evaluation'
Requires-Dist: insight[db] ==1.0-rc6 ; extra == 'evaluation'
Requires-Dist: psutil >=5.8.0 ; extra == 'evaluation'
Requires-Dist: pydantic ==1.10.13 ; extra == 'evaluation'
Requires-Dist: pyyaml ==6.0.1 ; extra == 'evaluation'
Requires-Dist: synthesized-datasets ==1.3 ; extra == 'evaluation'
Provides-Extra: test
Requires-Dist: cython >=3.0.2 ; extra == 'test'
Requires-Dist: hypothesis ; extra == 'test'
Requires-Dist: pytest ; extra == 'test'
Requires-Dist: pytest-cov ; extra == 'test'
Requires-Dist: pytest-split ; extra == 'test'
Requires-Dist: pytest-timeout ; extra == 'test'
Requires-Dist: scikit-learn ; extra == 'test'
Requires-Dist: synthesized-datasets ==1.3 ; extra == 'test'
